huaweicloudsdkgaussdbfornosql/__init__.py
huaweicloudsdkgaussdbfornosql/v3/__init__.py
huaweicloudsdkgaussdbfornosql/v3/gaussdbfornosql_async_client.py
huaweicloudsdkgaussdbfornosql/v3/gaussdbfornosql_client.py
huaweicloudsdkgaussdbfornosql/v3/model/__init__.py
huaweicloudsdkgaussdbfornosql/v3/model/action_body.py
huaweicloudsdkgaussdbfornosql/v3/model/api_version_response.py
huaweicloudsdkgaussdbfornosql/v3/model/applicable_instance_rsp.py
huaweicloudsdkgaussdbfornosql/v3/model/apply_configuration_request.py
huaweicloudsdkgaussdbfornosql/v3/model/apply_configuration_request_body.py
huaweicloudsdkgaussdbfornosql/v3/model/apply_configuration_response.py
huaweicloudsdkgaussdbfornosql/v3/model/apply_configuration_to_instances_request.py
huaweicloudsdkgaussdbfornosql/v3/model/apply_configuration_to_instances_request_body.py
huaweicloudsdkgaussdbfornosql/v3/model/apply_configuration_to_instances_response.py
huaweicloudsdkgaussdbfornosql/v3/model/apply_history_rsp.py
huaweicloudsdkgaussdbfornosql/v3/model/availability_zone_detail.py
huaweicloudsdkgaussdbfornosql/v3/model/backup.py
huaweicloudsdkgaussdbfornosql/v3/model/backup_policy.py
huaweicloudsdkgaussdbfornosql/v3/model/backup_strategy_option.py
huaweicloudsdkgaussdbfornosql/v3/model/backup_strategy_result.py
huaweicloudsdkgaussdbfornosql/v3/model/batch_delete_manual_backup_request.py
huaweicloudsdkgaussdbfornosql/v3/model/batch_delete_manual_backup_request_body.py
huaweicloudsdkgaussdbfornosql/v3/model/batch_delete_manual_backup_response.py
huaweicloudsdkgaussdbfornosql/v3/model/batch_tag_action_request.py
huaweicloudsdkgaussdbfornosql/v3/model/batch_tag_action_request_body.py
huaweicloudsdkgaussdbfornosql/v3/model/batch_tag_action_response.py
huaweicloudsdkgaussdbfornosql/v3/model/batch_tag_action_tag_option.py
huaweicloudsdkgaussdbfornosql/v3/model/batch_upgrade_database_version_request.py
huaweicloudsdkgaussdbfornosql/v3/model/batch_upgrade_database_version_request_body.py
huaweicloudsdkgaussdbfornosql-3.1.184.dist-info/METADATA
huaweicloudsdkgaussdbfornosql-3.1.184.dist-info/WHEEL
huaweicloudsdkgaussdbfornosql-3.1.184.dist-info/licenses/LICENSE
huaweicloudsdkgaussdbfornosql-3.1.184.dist-info/RECORD
